{
  "status": 1,
  "msg": "OK",
  "data": {
    "total": 3,
    "items": [{
      "id": 3,
      "shortname": "铸造厂",
      "company": "沈阳市东北铸造厂",
      "companycode": "",
      "address": "沈阳浑河西二十街西100米",
      "location": "{\"latitude\":\"41.72274\",\"longitude\":\"123.202004\"}",
      "bizownername": "铸造厂",
      "bizownertel": "024-88677777",
      "bizownerphone": "13077777777",
      "taxpayeridentification": "1",
      "bank": "1",
      "bankaccount": "1",
      "financechiefname": null,
      "financechieftel": "1",
      "financechiefphone": "1",
      "companytypecode": "",
      "dataauthorityid": null,
      "isspecialpower": 0,
      "superiorunitcode": 0,
      "endtime": 1594884100000,
      "pic": "zhuzaochang.jpg"
    }, {
      "id": 2,
      "shortname": "物流园",
      "company": "沈阳市物流园",
      "companycode": "",
      "address": "沈阳经济技术开发区沈新西路292-1号-1#",
      "location": "{\"latitude\":\"41.823252\",\"longitude\":\"123.495133\"}",
      "bizownername": "沈阳世纪联合东北仓储",
      "bizownertel": "024-88676666",
      "bizownerphone": "13066666666",
      "taxpayeridentification": "1",
      "bank": "1",
      "bankaccount": "1",
      "financechiefname": null,
      "financechieftel": "1",
      "financechiefphone": "1",
      "companytypecode": "1",
      "dataauthorityid": null,
      "isspecialpower": 0,
      "superiorunitcode": 0,
      "endtime": 1577512083000,
      "pic": "wuliuyuan.jpg"
    }, {
      "id": 1,
      "shortname": "铁西区政府",
      "company": "沈阳市铁西区政府",
      "companycode": "123123",
      "address": "辽宁省沈阳市铁西区北二西路重工北街37号",
      "location": "{\"latitude\":\"41.826984\",\"longitude\":\"123.340501\"}",
      "bizownername": "铁西区政府",
      "bizownertel": "024-88678888",
      "bizownerphone": "13088888888",
      "taxpayeridentification": "1",
      "bank": "1",
      "bankaccount": "1",
      "financechiefname": null,
      "financechieftel": "1",
      "financechiefphone": "1",
      "companytypecode": "03",
      "dataauthorityid": null,
      "isspecialpower": 0,
      "superiorunitcode": 0,
      "endtime": 1577512083000,
      "pic": "tiexiquzhengfu.jpg"
    }]
  },
  "succeeded": true,
  "ok": true
}