{"status":1,"msg":"OK","data":"{\"account\":\"lizhi\",\"name\":\"李志\",\"permission\":[{\"functionid\":1,\"updatefunction\":0,\"selectfunction\":0,\"deletefunction\":0,\"functionname\":\"electrician\",\"addfunction\":0},{\"functionid\":2,\"updatefunction\":0,\"selectfunction\":0,\"deletefunction\":0,\"functionname\":\"customer\",\"addfunction\":0},{\"functionid\":3,\"updatefunction\":0,\"selectfunction\":0,\"deletefunction\":0,\"functionname\":\"typeDevice\",\"addfunction\":0},{\"functionid\":4,\"updatefunction\":0,\"selectfunction\":0,\"deletefunction\":0,\"functionname\":\"magDomain\",\"addfunction\":0},{\"functionid\":5,\"updatefunction\":0,\"selectfunction\":0,\"deletefunction\":0,\"functionname\":\"gateWay\",\"addfunction\":0},{\"functionid\":6,\"updatefunction\":0,\"selectfunction\":0,\"deletefunction\":0,\"functionname\":\"magDomainElectrician\",\"addfunction\":0},{\"functionid\":7,\"updatefunction\":0,\"selectfunction\":0,\"deletefunction\":0,\"functionname\":\"electricitySubstation\",\"addfunction\":0},{\"functionid\":8,\"updatefunction\":0,\"selectfunction\":0,\"deletefunction\":0,\"functionname\":\"magDomainElectricity\",\"addfunction\":0},{\"functionid\":9,\"updatefunction\":0,\"selectfunction\":0,\"deletefunction\":0,\"functionname\":\"incomingCabinet\",\"addfunction\":0},{\"functionid\":10,\"updatefunction\":0,\"selectfunction\":0,\"deletefunction\":0,\"functionname\":\"capacitorCabinet\",\"addfunction\":0},{\"functionid\":11,\"updatefunction\":0,\"selectfunction\":0,\"deletefunction\":0,\"functionname\":\"lowCabinet\",\"addfunction\":0},{\"functionid\":12,\"updatefunction\":0,\"selectfunction\":0,\"deletefunction\":0,\"functionname\":\"transformer\",\"addfunction\":0},{\"functionid\":13,\"updatefunction\":0,\"selectfunction\":0,\"deletefunction\":0,\"functionname\":\"elecmeter\",\"addfunction\":0},{\"functionid\":14,\"updatefunction\":0,\"selectfunction\":0,\"deletefunction\":0,\"functionname\":\"electricitysubstationVideo\",\"addfunction\":0},{\"functionid\":15,\"updatefunction\":0,\"selectfunction\":0,\"deletefunction\":0,\"functionname\":\"electricitySubstationPic\",\"addfunction\":0},{\"functionid\":16,\"updatefunction\":0,\"selectfunction\":0,\"deletefunction\":0,\"functionname\":\"electricianPic\",\"addfunction\":0},{\"functionid\":17,\"updatefunction\":0,\"selectfunction\":0,\"deletefunction\":0,\"functionname\":\"gatewayInstructions\",\"addfunction\":0},{\"functionid\":18,\"updatefunction\":0,\"selectfunction\":0,\"deletefunction\":0,\"functionname\":\"sysRole\",\"addfunction\":0},{\"functionid\":19,\"updatefunction\":0,\"selectfunction\":0,\"deletefunction\":0,\"functionname\":\"sysFunction\",\"addfunction\":0},{\"functionid\":20,\"updatefunction\":0,\"selectfunction\":0,\"deletefunction\":0,\"functionname\":\"sysRoleFunction\",\"addfunction\":0},{\"functionid\":21,\"updatefunction\":0,\"selectfunction\":0,\"deletefunction\":0,\"functionname\":\"sysElectricianRole\",\"addfunction\":0}]}","succeeded":true,"ok":true}